w7x/__init__.py
w7x/__main__.py
w7x/compatibility.py
w7x/conf/config.yaml
w7x/config.py
w7x/core.py
w7x/lib/__init__.py
w7x/lib/dataclasses.py
w7x/lib/equilibrium.py
w7x/lib/profiles.py
w7x/lib/tfields.py
w7x/lib/timeout.py
w7x/lib/utils.py
w7x/lib/webdav.py
w7x/merge.py
w7x/model.py
w7x/plotting/__init__.py
w7x/plotting/extender.py
w7x/plotting/poincare.py
w7x/plotting/vmec.py
w7x/setup/presentation.py
w7x/setup/vmec/nn.py
w7x/setup/vmec/stellopt.py
w7x/simulation/__init__.py
w7x/simulation/backends/__init__.py
w7x/simulation/backends/local/__init__.py
w7x/simulation/backends/local/extender.py
w7x/simulation/backends/mock/__init__.py
w7x/simulation/backends/mock/flt.py
w7x/simulation/backends/mock/vmec.py
w7x/simulation/backends/nn/vmec.py
w7x/simulation/backends/runner/__init__.py
w7x/simulation/backends/runner/base.py
w7x/simulation/backends/runner/coils.py
w7x/simulation/backends/runner/vmec.py
w7x/simulation/backends/slurm/__init__.py
w7x/simulation/backends/slurm/extender.py
w7x/simulation/backends/web_service/__init__.py
w7x/simulation/backends/web_service/base.py
w7x/simulation/backends/web_service/coils.py
w7x/simulation/backends/web_service/components.py
w7x/simulation/backends/web_service/extender.py
w7x/simulation/backends/web_service/flt.py
w7x/simulation/backends/web_service/vmec.py
w7x/simulation/coils.py
w7x/simulation/components.py
w7x/simulation/extender.py
w7x/simulation/fieldlines.py
w7x/simulation/flavors/__init__.py
w7x/simulation/flavors/equilibrium.py
w7x/simulation/flavors/field_line_tracer.py
w7x/simulation/flt.py
w7x/simulation/vmec.py
w7x/state.py
w7x/switches.py
w7x-0.6.0.dist-info/LICENSE.rst
w7x-0.6.0.dist-info/METADATA
w7x-0.6.0.dist-info/WHEEL
w7x-0.6.0.dist-info/entry_points.txt
w7x-0.6.0.dist-info/RECORD
