Metadata-Version: 2.1
Name: w7x
Version: 0.6.0
Summary: The w7x package is a simulation framework that defines interfaces for simulation codes with interchangeable backends, computation pipelines in a directed acyclic graph that communicate via a central state.
Home-page: https://gitlab.mpcdf.mpg.de/dboe/w7x
License: MIT
Keywords: Wendelstein 7-X,simulation,state,field line tracer,vmec,extender,numerical modeling,distributed computing
Author: Daniel Böckenhoff
Author-email: dboe@ipp.mpg.de
Requires-Python: >=3.8,<4.0
Classifier: Development Status :: 3 - Alpha
Classifier: License :: OSI Approved :: MIT License
Classifier: Programming Language :: Python
Classifier: Programming Language :: Python :: 3
Classifier: Programming Language :: Python :: 3.8
Classifier: Programming Language :: Python :: 3.9
Classifier: Programming Language :: Python :: 3.10
Classifier: Programming Language :: Python :: 3.11
Provides-Extra: dot
Provides-Extra: hyperopt
Requires-Dist: dask[complete,distributed] (>=2021.06.00)
Requires-Dist: dill
Requires-Dist: gitpython (>=3.1.31,<4.0.0)
Requires-Dist: graphviz ; extra == "dot"
Requires-Dist: hydra_core
Requires-Dist: hyperopt ; extra == "hyperopt"
Requires-Dist: netCDF4
Requires-Dist: numpy (>=1.20.0)
Requires-Dist: osa
Requires-Dist: pathlib ; python_version < "3.10"
Requires-Dist: requests
Requires-Dist: rna[pyqtgraph] (>=0.11.0)
Requires-Dist: scikit-learn (>0.0)
Requires-Dist: scipy (>=1.9.2)
Requires-Dist: tfields[io] (>=0.5.0)
Project-URL: Documentation, https://dboe.pages.mpcdf.de/w7x
Project-URL: Repository, https://gitlab.mpcdf.mpg.de/dboe/w7x
